{
	"parent": "item/handheld",
	"textures": {
		"layer0": "item/crossbow_standby"
	},
    "display": {
        "thirdperson_righthand": {
            "rotation": [ -90, 0, -60 ],
            "translation": [ 2, 0.1, -3 ],
            "scale": [ 0.9, 0.9, 0.9 ]
        },
        "thirdperson_lefthand": {
            "rotation": [ -90, 0, 30 ],
            "translation": [ 2, 0.1, -3 ],
            "scale": [ 0.9, 0.9, 0.9 ]
        },
        "firstperson_righthand": {
            "rotation": [ -90, 0, -55 ],
            "translation": [ 1.13, 3.2, 1.13],
            "scale": [ 0.68, 0.68, 0.68 ]
        },
        "firstperson_lefthand": {
            "rotation": [ -90, 0, 35 ],
            "translation": [ 1.13, 3.2, 1.13],
            "scale": [ 0.68, 0.68, 0.68 ]
        }
    },
	"overrides": [
		{"predicate":{"custom_model_data":1},"model":"item/crossbow/crossbow1"},
		{"predicate":{"custom_model_data":2},"model":"item/crossbow/crossbow2"},
		{"predicate":{"custom_model_data":3},"model":"item/crossbow/crossbow3"},
		{"predicate":{"custom_model_data":4},"model":"item/crossbow/crossbow4"},
		{"predicate":{"custom_model_data":5},"model":"item/crossbow/crossbow5"},
		{"predicate":{"custom_model_data":6},"model":"item/crossbow/crossbow6"},
		{"predicate":{"custom_model_data":7},"model":"item/crossbow/crossbow7"},
		{"predicate":{"custom_model_data":8},"model":"item/crossbow/crossbow8"},
		{"predicate":{"custom_model_data":9},"model":"item/crossbow/crossbow9"},
		{"predicate":{"custom_model_data":10},"model":"item/crossbow/crossbow10"},
		{"predicate":{"custom_model_data":11},"model":"item/crossbow/crossbow11"},
		{"predicate":{"custom_model_data":12},"model":"item/crossbow/crossbow12"},
		{"predicate":{"custom_model_data":13},"model":"item/crossbow/crossbow13"},
		{"predicate":{"custom_model_data":14},"model":"item/crossbow/crossbow14"},
		{"predicate":{"custom_model_data":15},"model":"item/crossbow/crossbow15"},
		{"predicate":{"custom_model_data":16},"model":"item/crossbow/crossbow16"},
		{"predicate":{"custom_model_data":17},"model":"item/crossbow/crossbow17"},
		{"predicate":{"custom_model_data":18},"model":"item/crossbow/crossbow18"},
		{"predicate":{"custom_model_data":19},"model":"item/crossbow/crossbow19"},
		{"predicate":{"custom_model_data":20},"model":"item/crossbow/crossbow20"},
		{"predicate":{"custom_model_data":21},"model":"item/crossbow/crossbow21"},
		{"predicate":{"custom_model_data":22},"model":"item/crossbow/crossbow22"},
		{"predicate":{"custom_model_data":23},"model":"item/crossbow/crossbow23"},
		{"predicate":{"custom_model_data":24},"model":"item/crossbow/crossbow24"},
		{"predicate":{"custom_model_data":25},"model":"item/crossbow/crossbow25"},
		{"predicate":{"custom_model_data":26},"model":"item/crossbow/crossbow26"},
		{"predicate":{"custom_model_data":27},"model":"item/crossbow/crossbow27"},
		{"predicate":{"custom_model_data":28},"model":"item/crossbow/crossbow28"},
		{"predicate":{"custom_model_data":29},"model":"item/crossbow/crossbow29"},
		{"predicate":{"custom_model_data":30},"model":"item/crossbow/crossbow30"},
		{"predicate":{"custom_model_data":31},"model":"item/crossbow/crossbow31"},
		{"predicate":{"custom_model_data":32},"model":"item/crossbow/crossbow32"},
		{"predicate":{"custom_model_data":33},"model":"item/crossbow/crossbow33"},
		{"predicate":{"custom_model_data":34},"model":"item/crossbow/crossbow34"},
		{"predicate":{"custom_model_data":35},"model":"item/crossbow/crossbow35"},
		{"predicate":{"custom_model_data":36},"model":"item/crossbow/crossbow36"},
		{"predicate":{"custom_model_data":37},"model":"item/crossbow/crossbow37"},
		{"predicate":{"custom_model_data":38},"model":"item/crossbow/crossbow38"},
		{"predicate":{"custom_model_data":39},"model":"item/crossbow/crossbow39"},
		{"predicate":{"custom_model_data":40},"model":"item/crossbow/crossbow40"},
		{"predicate":{"custom_model_data":41},"model":"item/crossbow/crossbow41"},
		{"predicate":{"custom_model_data":42},"model":"item/crossbow/crossbow42"},
		{"predicate":{"custom_model_data":43},"model":"item/crossbow/crossbow43"},
		{"predicate":{"custom_model_data":44},"model":"item/crossbow/crossbow44"},
		{"predicate":{"custom_model_data":45},"model":"item/crossbow/crossbow45"},
		{"predicate":{"custom_model_data":46},"model":"item/crossbow/crossbow46"},
		{"predicate":{"custom_model_data":47},"model":"item/crossbow/crossbow47"},
		{"predicate":{"custom_model_data":48},"model":"item/crossbow/crossbow48"},
		{"predicate":{"custom_model_data":49},"model":"item/crossbow/crossbow49"},
		{"predicate":{"custom_model_data":50},"model":"item/crossbow/crossbow50"},
		{"predicate":{"custom_model_data":1, "charged": 1},"model":"item/crossbow/charged/crossbow1"},
		{"predicate":{"custom_model_data":2, "charged": 1},"model":"item/crossbow/charged/crossbow2"},
		{"predicate":{"custom_model_data":3, "charged": 1},"model":"item/crossbow/charged/crossbow3"},
		{"predicate":{"custom_model_data":4, "charged": 1},"model":"item/crossbow/charged/crossbow4"},
		{"predicate":{"custom_model_data":5, "charged": 1},"model":"item/crossbow/charged/crossbow5"},
		{"predicate":{"custom_model_data":6, "charged": 1},"model":"item/crossbow/charged/crossbow6"},
		{"predicate":{"custom_model_data":7, "charged": 1},"model":"item/crossbow/charged/crossbow7"},
		{"predicate":{"custom_model_data":8, "charged": 1},"model":"item/crossbow/charged/crossbow8"},
		{"predicate":{"custom_model_data":9, "charged": 1},"model":"item/crossbow/charged/crossbow9"},
		{"predicate":{"custom_model_data":10, "charged": 1},"model":"item/crossbow/charged/crossbow10"},
		{"predicate":{"custom_model_data":11, "charged": 1},"model":"item/crossbow/charged/crossbow11"},
		{"predicate":{"custom_model_data":12, "charged": 1},"model":"item/crossbow/charged/crossbow12"},
		{"predicate":{"custom_model_data":13, "charged": 1},"model":"item/crossbow/charged/crossbow13"},
		{"predicate":{"custom_model_data":14, "charged": 1},"model":"item/crossbow/charged/crossbow14"},
		{"predicate":{"custom_model_data":15, "charged": 1},"model":"item/crossbow/charged/crossbow15"},
		{"predicate":{"custom_model_data":16, "charged": 1},"model":"item/crossbow/charged/crossbow16"},
		{"predicate":{"custom_model_data":17, "charged": 1},"model":"item/crossbow/charged/crossbow17"},
		{"predicate":{"custom_model_data":18, "charged": 1},"model":"item/crossbow/charged/crossbow18"},
		{"predicate":{"custom_model_data":19, "charged": 1},"model":"item/crossbow/charged/crossbow19"},
		{"predicate":{"custom_model_data":20, "charged": 1},"model":"item/crossbow/charged/crossbow20"},
		{"predicate":{"custom_model_data":21, "charged": 1},"model":"item/crossbow/charged/crossbow21"},
		{"predicate":{"custom_model_data":22, "charged": 1},"model":"item/crossbow/charged/crossbow22"},
		{"predicate":{"custom_model_data":23, "charged": 1},"model":"item/crossbow/charged/crossbow23"},
		{"predicate":{"custom_model_data":24, "charged": 1},"model":"item/crossbow/charged/crossbow24"},
		{"predicate":{"custom_model_data":25, "charged": 1},"model":"item/crossbow/charged/crossbow25"},
		{"predicate":{"custom_model_data":26, "charged": 1},"model":"item/crossbow/charged/crossbow26"},
		{"predicate":{"custom_model_data":27, "charged": 1},"model":"item/crossbow/charged/crossbow27"},
		{"predicate":{"custom_model_data":28, "charged": 1},"model":"item/crossbow/charged/crossbow28"},
		{"predicate":{"custom_model_data":29, "charged": 1},"model":"item/crossbow/charged/crossbow29"},
		{"predicate":{"custom_model_data":30, "charged": 1},"model":"item/crossbow/charged/crossbow30"},
		{"predicate":{"custom_model_data":31, "charged": 1},"model":"item/crossbow/charged/crossbow31"},
		{"predicate":{"custom_model_data":32, "charged": 1},"model":"item/crossbow/charged/crossbow32"},
		{"predicate":{"custom_model_data":32, "charged": 1},"model":"item/crossbow/charged/crossbow33"},
		{"predicate":{"custom_model_data":33, "charged": 1},"model":"item/crossbow/charged/crossbow34"},
		{"predicate":{"custom_model_data":35, "charged": 1},"model":"item/crossbow/charged/crossbow35"},
		{"predicate":{"custom_model_data":36, "charged": 1},"model":"item/crossbow/charged/crossbow36"},
		{"predicate":{"custom_model_data":37, "charged": 1},"model":"item/crossbow/charged/crossbow37"},
		{"predicate":{"custom_model_data":37, "charged": 1},"model":"item/crossbow/charged/crossbow37"},
		{"predicate":{"custom_model_data":38, "charged": 1},"model":"item/crossbow/charged/crossbow38"},
		{"predicate":{"custom_model_data":39, "charged": 1},"model":"item/crossbow/charged/crossbow39"},
		{"predicate":{"custom_model_data":40, "charged": 1},"model":"item/crossbow/charged/crossbow40"},
		{"predicate":{"custom_model_data":41, "charged": 1},"model":"item/crossbow/charged/crossbow41"},
		{"predicate":{"custom_model_data":42, "charged": 1},"model":"item/crossbow/charged/crossbow42"},
		{"predicate":{"custom_model_data":43, "charged": 1},"model":"item/crossbow/charged/crossbow43"},
		{"predicate":{"custom_model_data":44, "charged": 1},"model":"item/crossbow/charged/crossbow44"},
		{"predicate":{"custom_model_data":45, "charged": 1},"model":"item/crossbow/charged/crossbow45"},
		{"predicate":{"custom_model_data":46, "charged": 1},"model":"item/crossbow/charged/crossbow46"},
		{"predicate":{"custom_model_data":47, "charged": 1},"model":"item/crossbow/charged/crossbow47"},
		{"predicate":{"custom_model_data":48, "charged": 1},"model":"item/crossbow/charged/crossbow48"},
		{"predicate":{"custom_model_data":49, "charged": 1},"model":"item/crossbow/charged/crossbow49"},
		{"predicate":{"custom_model_data":50, "charged": 1},"model":"item/crossbow/charged/crossbow50"}
	]
}
