{
  "parent": "item/handheld",
  "textures": {
    "layer0": "item/blaze_rod"
  },
  "overrides": [
    {"predicate": { "custom_model_data": 1 },"model": "item/sentineru"},
    {"predicate": { "custom_model_data": 2 },"model": "item/sentineru2"},
    {"predicate": { "custom_model_data": 3 },"model": "item/ptoluwe"},
    {"predicate": { "custom_model_data": 4 },"model": "item/furatora"},
    {"predicate": { "custom_model_data": 5 },"model": "item/kirifuda"},
    {"predicate": { "custom_model_data": 6 },"model": "item/masutelifu"},
    {"predicate": { "custom_model_data": 7 },"model": "item/kirifuda2"},
    {"predicate": { "custom_model_data": 8 },"model": "item/mozan"},
    {"predicate": { "custom_model_data": 9 },"model": "item/wintyesuta"}
  ]
}
