{
	"credit": "Made with Blockbench",
	"textures": {
		"0": "dx0812",
		"particle": "dx0812"
	},
	"elements": [
		{
			"name": "dx0812_0",
			"from": [9, 0, 0.5],
			"to": [9.5, 0.5, 4],
			"faces": {
				"north": {"uv": [9.5, 0.5, 9, 1], "texture": "#0"},
				"east": {"uv": [9, 0.5, 9.5, 4], "rotation": 90, "texture": "#0"},
				"south": {"uv": [9, 3.5, 9.5, 4], "texture": "#0"},
				"west": {"uv": [9, 0.5, 9.5, 4], "rotation": 270, "texture": "#0"},
				"up": {"uv": [9, 0.5, 9.5, 4], "texture": "#0"},
				"down": {"uv": [9, 4, 9.5, 0.5], "texture": "#0"}
			}
		},
		{
			"name": "dx0812_1",
			"from": [11, 0, 0.5],
			"to": [11.5, 0.5, 1],
			"faces": {
				"north": {"uv": [11.5, 0.5, 11, 1], "texture": "#0"},
				"east": {"uv": [11, 0.5, 11.5, 1], "rotation": 90, "texture": "#0"},
				"south": {"uv": [11, 0.5, 11.5, 1], "texture": "#0"},
				"west": {"uv": [11, 0.5, 11.5, 1], "rotation": 270, "texture": "#0"},
				"up": {"uv": [11, 0.5, 11.5, 1], "texture": "#0"},
				"down": {"uv": [11, 1, 11.5, 0.5], "texture": "#0"}
			}
		},
		{
			"name": "dx0812_2",
			"from": [9.5, 0, 1],
			"to": [10, 0.5, 2],
			"faces": {
				"north": {"uv": [10, 1, 9.5, 1.5], "texture": "#0"},
				"east": {"uv": [9.5, 1, 10, 2], "rotation": 90, "texture": "#0"},
				"south": {"uv": [9.5, 1.5, 10, 2], "texture": "#0"},
				"west": {"uv": [9.5, 1, 10, 2], "rotation": 270, "texture": "#0"},
				"up": {"uv": [9.5, 1, 10, 2], "texture": "#0"},
				"down": {"uv": [9.5, 2, 10, 1], "texture": "#0"}
			}
		},
		{
			"name": "dx0812_3",
			"from": [10.5, 0, 1],
			"to": [11, 0.5, 2],
			"faces": {
				"north": {"uv": [11, 1, 10.5, 1.5], "texture": "#0"},
				"east": {"uv": [10.5, 1, 11, 2], "rotation": 90, "texture": "#0"},
				"south": {"uv": [10.5, 1.5, 11, 2], "texture": "#0"},
				"west": {"uv": [10.5, 1, 11, 2], "rotation": 270, "texture": "#0"},
				"up": {"uv": [10.5, 1, 11, 2], "texture": "#0"},
				"down": {"uv": [10.5, 2, 11, 1], "texture": "#0"}
			}
		},
		{
			"name": "dx0812_4",
			"from": [8.5, 0, 1.5],
			"to": [9, 0.5, 2],
			"faces": {
				"north": {"uv": [9, 1.5, 8.5, 2], "texture": "#0"},
				"east": {"uv": [8.5, 1.5, 9, 2], "rotation": 90, "texture": "#0"},
				"south": {"uv": [8.5, 1.5, 9, 2], "texture": "#0"},
				"west": {"uv": [8.5, 1.5, 9, 2], "rotation": 270, "texture": "#0"},
				"up": {"uv": [8.5, 1.5, 9, 2], "texture": "#0"},
				"down": {"uv": [8.5, 2, 9, 1.5], "texture": "#0"}
			}
		},
		{
			"name": "dx0812_5",
			"from": [11, 0, 1.5],
			"to": [11.5, 0.5, 3],
			"faces": {
				"north": {"uv": [11.5, 1.5, 11, 2], "texture": "#0"},
				"east": {"uv": [11, 1.5, 11.5, 3], "rotation": 90, "texture": "#0"},
				"south": {"uv": [11, 2.5, 11.5, 3], "texture": "#0"},
				"west": {"uv": [11, 1.5, 11.5, 3], "rotation": 270, "texture": "#0"},
				"up": {"uv": [11, 1.5, 11.5, 3], "texture": "#0"},
				"down": {"uv": [11, 3, 11.5, 1.5], "texture": "#0"}
			}
		},
		{
			"name": "dx0812_6",
			"from": [10, 0, 2],
			"to": [10.5, 0.5, 3],
			"faces": {
				"north": {"uv": [10.5, 2, 10, 2.5], "texture": "#0"},
				"east": {"uv": [10, 2, 10.5, 3], "rotation": 90, "texture": "#0"},
				"south": {"uv": [10, 2.5, 10.5, 3], "texture": "#0"},
				"west": {"uv": [10, 2, 10.5, 3], "rotation": 270, "texture": "#0"},
				"up": {"uv": [10, 2, 10.5, 3], "texture": "#0"},
				"down": {"uv": [10, 3, 10.5, 2], "texture": "#0"}
			}
		},
		{
			"name": "dx0812_7",
			"from": [11.5, 0, 2],
			"to": [12, 0.5, 2.5],
			"faces": {
				"north": {"uv": [12, 2, 11.5, 2.5], "texture": "#0"},
				"east": {"uv": [11.5, 2, 12, 2.5], "rotation": 90, "texture": "#0"},
				"south": {"uv": [11.5, 2, 12, 2.5], "texture": "#0"},
				"west": {"uv": [11.5, 2, 12, 2.5], "rotation": 270, "texture": "#0"},
				"up": {"uv": [11.5, 2, 12, 2.5], "texture": "#0"},
				"down": {"uv": [11.5, 2.5, 12, 2], "texture": "#0"}
			}
		},
		{
			"name": "dx0812_8",
			"from": [8, 0, 2.5],
			"to": [8.5, 0.5, 3.5],
			"faces": {
				"north": {"uv": [8.5, 2.5, 8, 3], "texture": "#0"},
				"east": {"uv": [8, 2.5, 8.5, 3.5], "rotation": 90, "texture": "#0"},
				"south": {"uv": [8, 3, 8.5, 3.5], "texture": "#0"},
				"west": {"uv": [8, 2.5, 8.5, 3.5], "rotation": 270, "texture": "#0"},
				"up": {"uv": [8, 2.5, 8.5, 3.5], "texture": "#0"},
				"down": {"uv": [8, 3.5, 8.5, 2.5], "texture": "#0"}
			}
		},
		{
			"name": "dx0812_9",
			"from": [9.5, 0, 2.5],
			"to": [10, 0.5, 3.5],
			"faces": {
				"north": {"uv": [10, 2.5, 9.5, 3], "texture": "#0"},
				"east": {"uv": [9.5, 2.5, 10, 3.5], "rotation": 90, "texture": "#0"},
				"south": {"uv": [9.5, 3, 10, 3.5], "texture": "#0"},
				"west": {"uv": [9.5, 2.5, 10, 3.5], "rotation": 270, "texture": "#0"},
				"up": {"uv": [9.5, 2.5, 10, 3.5], "texture": "#0"},
				"down": {"uv": [9.5, 3.5, 10, 2.5], "texture": "#0"}
			}
		},
		{
			"name": "dx0812_10",
			"from": [10.5, 0, 2.5],
			"to": [11, 0.5, 3],
			"faces": {
				"north": {"uv": [11, 2.5, 10.5, 3], "texture": "#0"},
				"east": {"uv": [10.5, 2.5, 11, 3], "rotation": 90, "texture": "#0"},
				"south": {"uv": [10.5, 2.5, 11, 3], "texture": "#0"},
				"west": {"uv": [10.5, 2.5, 11, 3], "rotation": 270, "texture": "#0"},
				"up": {"uv": [10.5, 2.5, 11, 3], "texture": "#0"},
				"down": {"uv": [10.5, 3, 11, 2.5], "texture": "#0"}
			}
		},
		{
			"name": "dx0812_11",
			"from": [8.5, 0, 3],
			"to": [9, 0.5, 3.5],
			"faces": {
				"north": {"uv": [9, 3, 8.5, 3.5], "texture": "#0"},
				"east": {"uv": [8.5, 3, 9, 3.5], "rotation": 90, "texture": "#0"},
				"south": {"uv": [8.5, 3, 9, 3.5], "texture": "#0"},
				"west": {"uv": [8.5, 3, 9, 3.5], "rotation": 270, "texture": "#0"},
				"up": {"uv": [8.5, 3, 9, 3.5], "texture": "#0"},
				"down": {"uv": [8.5, 3.5, 9, 3], "texture": "#0"}
			}
		},
		{
			"name": "dx0812_12",
			"from": [10.5, 0, 3.5],
			"to": [11, 0.5, 4],
			"faces": {
				"north": {"uv": [11, 3.5, 10.5, 4], "texture": "#0"},
				"east": {"uv": [10.5, 3.5, 11, 4], "rotation": 90, "texture": "#0"},
				"south": {"uv": [10.5, 3.5, 11, 4], "texture": "#0"},
				"west": {"uv": [10.5, 3.5, 11, 4], "rotation": 270, "texture": "#0"},
				"up": {"uv": [10.5, 3.5, 11, 4], "texture": "#0"},
				"down": {"uv": [10.5, 4, 11, 3.5], "texture": "#0"}
			}
		},
		{
			"name": "dx0812_13",
			"from": [7.5, 0, 4],
			"to": [8.5, 0.5, 4.5],
			"faces": {
				"north": {"uv": [8.5, 4, 7.5, 4.5], "texture": "#0"},
				"east": {"uv": [8, 4, 8.5, 4.5], "rotation": 90, "texture": "#0"},
				"south": {"uv": [7.5, 4, 8.5, 4.5], "texture": "#0"},
				"west": {"uv": [7.5, 4, 8, 4.5], "rotation": 270, "texture": "#0"},
				"up": {"uv": [7.5, 4, 8.5, 4.5], "texture": "#0"},
				"down": {"uv": [7.5, 4.5, 8.5, 4], "texture": "#0"}
			}
		},
		{
			"name": "dx0812_14",
			"from": [7, 0, 4.5],
			"to": [7.5, 0.5, 8],
			"faces": {
				"north": {"uv": [7.5, 4.5, 7, 5], "texture": "#0"},
				"east": {"uv": [7, 4.5, 7.5, 8], "rotation": 90, "texture": "#0"},
				"south": {"uv": [7, 7.5, 7.5, 8], "texture": "#0"},
				"west": {"uv": [7, 4.5, 7.5, 8], "rotation": 270, "texture": "#0"},
				"up": {"uv": [7, 4.5, 7.5, 8], "texture": "#0"},
				"down": {"uv": [7, 8, 7.5, 4.5], "texture": "#0"}
			}
		},
		{
			"name": "dx0812_15",
			"from": [8, 0, 4.5],
			"to": [8.5, 0.5, 5.5],
			"faces": {
				"north": {"uv": [8.5, 4.5, 8, 5], "texture": "#0"},
				"east": {"uv": [8, 4.5, 8.5, 5.5], "rotation": 90, "texture": "#0"},
				"south": {"uv": [8, 5, 8.5, 5.5], "texture": "#0"},
				"west": {"uv": [8, 4.5, 8.5, 5.5], "rotation": 270, "texture": "#0"},
				"up": {"uv": [8, 4.5, 8.5, 5.5], "texture": "#0"},
				"down": {"uv": [8, 5.5, 8.5, 4.5], "texture": "#0"}
			}
		},
		{
			"name": "dx0812_16",
			"from": [9.5, 0, 4.5],
			"to": [10.5, 0.5, 6],
			"faces": {
				"north": {"uv": [10.5, 4.5, 9.5, 5], "texture": "#0"},
				"east": {"uv": [10, 4.5, 10.5, 6], "rotation": 90, "texture": "#0"},
				"south": {"uv": [9.5, 5.5, 10.5, 6], "texture": "#0"},
				"west": {"uv": [9.5, 4.5, 10, 6], "rotation": 270, "texture": "#0"},
				"up": {"uv": [9.5, 4.5, 10.5, 6], "texture": "#0"},
				"down": {"uv": [9.5, 6, 10.5, 4.5], "texture": "#0"}
			}
		},
		{
			"name": "dx0812_17",
			"from": [6.5, 0, 5],
			"to": [7, 0.5, 6],
			"faces": {
				"north": {"uv": [7, 5, 6.5, 5.5], "texture": "#0"},
				"east": {"uv": [6.5, 5, 7, 6], "rotation": 90, "texture": "#0"},
				"south": {"uv": [6.5, 5.5, 7, 6], "texture": "#0"},
				"west": {"uv": [6.5, 5, 7, 6], "rotation": 270, "texture": "#0"},
				"up": {"uv": [6.5, 5, 7, 6], "texture": "#0"},
				"down": {"uv": [6.5, 6, 7, 5], "texture": "#0"}
			}
		},
		{
			"name": "dx0812_18",
			"from": [7.5, 0, 5],
			"to": [8, 0.5, 6],
			"faces": {
				"north": {"uv": [8, 5, 7.5, 5.5], "texture": "#0"},
				"east": {"uv": [7.5, 5, 8, 6], "rotation": 90, "texture": "#0"},
				"south": {"uv": [7.5, 5.5, 8, 6], "texture": "#0"},
				"west": {"uv": [7.5, 5, 8, 6], "rotation": 270, "texture": "#0"},
				"up": {"uv": [7.5, 5, 8, 6], "texture": "#0"},
				"down": {"uv": [7.5, 6, 8, 5], "texture": "#0"}
			}
		},
		{
			"name": "dx0812_19",
			"from": [9, 0, 5],
			"to": [9.5, 0.5, 5.5],
			"faces": {
				"north": {"uv": [9.5, 5, 9, 5.5], "texture": "#0"},
				"east": {"uv": [9, 5, 9.5, 5.5], "rotation": 90, "texture": "#0"},
				"south": {"uv": [9, 5, 9.5, 5.5], "texture": "#0"},
				"west": {"uv": [9, 5, 9.5, 5.5], "rotation": 270, "texture": "#0"},
				"up": {"uv": [9, 5, 9.5, 5.5], "texture": "#0"},
				"down": {"uv": [9, 5.5, 9.5, 5], "texture": "#0"}
			}
		},
		{
			"name": "dx0812_20",
			"from": [9, 0, 6],
			"to": [10, 0.5, 7],
			"faces": {
				"north": {"uv": [10, 6, 9, 6.5], "texture": "#0"},
				"east": {"uv": [9.5, 6, 10, 7], "rotation": 90, "texture": "#0"},
				"south": {"uv": [9, 6.5, 10, 7], "texture": "#0"},
				"west": {"uv": [9, 6, 9.5, 7], "rotation": 270, "texture": "#0"},
				"up": {"uv": [9, 6, 10, 7], "texture": "#0"},
				"down": {"uv": [9, 7, 10, 6], "texture": "#0"}
			}
		},
		{
			"name": "dx0812_21",
			"from": [7.5, 0, 6.5],
			"to": [8.5, 0.5, 8],
			"faces": {
				"north": {"uv": [8.5, 6.5, 7.5, 7], "texture": "#0"},
				"east": {"uv": [8, 6.5, 8.5, 8], "rotation": 90, "texture": "#0"},
				"south": {"uv": [7.5, 7.5, 8.5, 8], "texture": "#0"},
				"west": {"uv": [7.5, 6.5, 8, 8], "rotation": 270, "texture": "#0"},
				"up": {"uv": [7.5, 6.5, 8.5, 8], "texture": "#0"},
				"down": {"uv": [7.5, 8, 8.5, 6.5], "texture": "#0"}
			}
		},
		{
			"name": "dx0812_22",
			"from": [8.5, 0, 6.5],
			"to": [9, 0.5, 7],
			"faces": {
				"north": {"uv": [9, 6.5, 8.5, 7], "texture": "#0"},
				"east": {"uv": [8.5, 6.5, 9, 7], "rotation": 90, "texture": "#0"},
				"south": {"uv": [8.5, 6.5, 9, 7], "texture": "#0"},
				"west": {"uv": [8.5, 6.5, 9, 7], "rotation": 270, "texture": "#0"},
				"up": {"uv": [8.5, 6.5, 9, 7], "texture": "#0"},
				"down": {"uv": [8.5, 7, 9, 6.5], "texture": "#0"}
			}
		},
		{
			"name": "dx0812_23",
			"from": [6.5, 0, 7],
			"to": [7, 0.5, 8],
			"faces": {
				"north": {"uv": [7, 7, 6.5, 7.5], "texture": "#0"},
				"east": {"uv": [6.5, 7, 7, 8], "rotation": 90, "texture": "#0"},
				"south": {"uv": [6.5, 7.5, 7, 8], "texture": "#0"},
				"west": {"uv": [6.5, 7, 7, 8], "rotation": 270, "texture": "#0"},
				"up": {"uv": [6.5, 7, 7, 8], "texture": "#0"},
				"down": {"uv": [6.5, 8, 7, 7], "texture": "#0"}
			}
		},
		{
			"name": "dx0812_24",
			"from": [9.5, 0, 7],
			"to": [10, 0.5, 7.5],
			"faces": {
				"north": {"uv": [10, 7, 9.5, 7.5], "texture": "#0"},
				"east": {"uv": [9.5, 7, 10, 7.5], "rotation": 90, "texture": "#0"},
				"south": {"uv": [9.5, 7, 10, 7.5], "texture": "#0"},
				"west": {"uv": [9.5, 7, 10, 7.5], "rotation": 270, "texture": "#0"},
				"up": {"uv": [9.5, 7, 10, 7.5], "texture": "#0"},
				"down": {"uv": [9.5, 7.5, 10, 7], "texture": "#0"}
			}
		},
		{
			"name": "dx0812_25",
			"from": [8.5, 0, 7.5],
			"to": [9, 0.5, 8.5],
			"faces": {
				"north": {"uv": [9, 7.5, 8.5, 8], "texture": "#0"},
				"east": {"uv": [8.5, 7.5, 9, 8.5], "rotation": 90, "texture": "#0"},
				"south": {"uv": [8.5, 8, 9, 8.5], "texture": "#0"},
				"west": {"uv": [8.5, 7.5, 9, 8.5], "rotation": 270, "texture": "#0"},
				"up": {"uv": [8.5, 7.5, 9, 8.5], "texture": "#0"},
				"down": {"uv": [8.5, 8.5, 9, 7.5], "texture": "#0"}
			}
		},
		{
			"name": "dx0812_26",
			"from": [7.5, 0, 8],
			"to": [8, 0.5, 9],
			"faces": {
				"north": {"uv": [8, 8, 7.5, 8.5], "texture": "#0"},
				"east": {"uv": [7.5, 8, 8, 9], "rotation": 90, "texture": "#0"},
				"south": {"uv": [7.5, 8.5, 8, 9], "texture": "#0"},
				"west": {"uv": [7.5, 8, 8, 9], "rotation": 270, "texture": "#0"},
				"up": {"uv": [7.5, 8, 8, 9], "texture": "#0"},
				"down": {"uv": [7.5, 9, 8, 8], "texture": "#0"}
			}
		},
		{
			"name": "dx0812_27",
			"from": [8, 0, 8.5],
			"to": [8.5, 0.5, 9],
			"faces": {
				"north": {"uv": [8.5, 8.5, 8, 9], "texture": "#0"},
				"east": {"uv": [8, 8.5, 8.5, 9], "rotation": 90, "texture": "#0"},
				"south": {"uv": [8, 8.5, 8.5, 9], "texture": "#0"},
				"west": {"uv": [8, 8.5, 8.5, 9], "rotation": 270, "texture": "#0"},
				"up": {"uv": [8, 8.5, 8.5, 9], "texture": "#0"},
				"down": {"uv": [8, 9, 8.5, 8.5], "texture": "#0"}
			}
		},
		{
			"name": "dx0812_28",
			"from": [7, 0, 9],
			"to": [7.5, 0.5, 12],
			"faces": {
				"north": {"uv": [7.5, 9, 7, 9.5], "texture": "#0"},
				"east": {"uv": [7, 9, 7.5, 12], "rotation": 90, "texture": "#0"},
				"south": {"uv": [7, 11.5, 7.5, 12], "texture": "#0"},
				"west": {"uv": [7, 9, 7.5, 12], "rotation": 270, "texture": "#0"},
				"up": {"uv": [7, 9, 7.5, 12], "texture": "#0"},
				"down": {"uv": [7, 12, 7.5, 9], "texture": "#0"}
			}
		},
		{
			"name": "dx0812_29",
			"from": [7.5, 0, 9.5],
			"to": [8, 0.5, 10.5],
			"faces": {
				"north": {"uv": [8, 9.5, 7.5, 10], "texture": "#0"},
				"east": {"uv": [7.5, 9.5, 8, 10.5], "rotation": 90, "texture": "#0"},
				"south": {"uv": [7.5, 10, 8, 10.5], "texture": "#0"},
				"west": {"uv": [7.5, 9.5, 8, 10.5], "rotation": 270, "texture": "#0"},
				"up": {"uv": [7.5, 9.5, 8, 10.5], "texture": "#0"},
				"down": {"uv": [7.5, 10.5, 8, 9.5], "texture": "#0"}
			}
		},
		{
			"name": "dx0812_30",
			"from": [6.5, 0, 10],
			"to": [7, 0.5, 10.5],
			"faces": {
				"north": {"uv": [7, 10, 6.5, 10.5], "texture": "#0"},
				"east": {"uv": [6.5, 10, 7, 10.5], "rotation": 90, "texture": "#0"},
				"south": {"uv": [6.5, 10, 7, 10.5], "texture": "#0"},
				"west": {"uv": [6.5, 10, 7, 10.5], "rotation": 270, "texture": "#0"},
				"up": {"uv": [6.5, 10, 7, 10.5], "texture": "#0"},
				"down": {"uv": [6.5, 10.5, 7, 10], "texture": "#0"}
			}
		},
		{
			"name": "dx0812_31",
			"from": [6.5, 0, 11],
			"to": [7, 0.5, 16],
			"faces": {
				"north": {"uv": [7, 11, 6.5, 11.5], "texture": "#0"},
				"east": {"uv": [6.5, 11, 7, 16], "rotation": 90, "texture": "#0"},
				"south": {"uv": [6.5, 15.5, 7, 16], "texture": "#0"},
				"west": {"uv": [6.5, 11, 7, 16], "rotation": 270, "texture": "#0"},
				"up": {"uv": [6.5, 11, 7, 16], "texture": "#0"},
				"down": {"uv": [6.5, 16, 7, 11], "texture": "#0"}
			}
		},
		{
			"name": "dx0812_32",
			"from": [6, 0, 12],
			"to": [6.5, 0.5, 16],
			"faces": {
				"north": {"uv": [6.5, 12, 6, 12.5], "texture": "#0"},
				"east": {"uv": [6, 12, 6.5, 16], "rotation": 90, "texture": "#0"},
				"south": {"uv": [6, 15.5, 6.5, 16], "texture": "#0"},
				"west": {"uv": [6, 12, 6.5, 16], "rotation": 270, "texture": "#0"},
				"up": {"uv": [6, 12, 6.5, 16], "texture": "#0"},
				"down": {"uv": [6, 16, 6.5, 12], "texture": "#0"}
			}
		}
	],
	"display": {
		"thirdperson_righthand": {
			"scale": [0, 0, 0]
		},
		"thirdperson_lefthand": {
			"scale": [0, 0, 0]
		},
		"firstperson_righthand": {
			"rotation": [77, -13, 88],
			"translation": [-0.5, 4.75, -5.25]
		},
		"firstperson_lefthand": {
			"rotation": [-95, 180, -102],
			"translation": [-2.75, 5.75, -1.75]
		},
		"ground": {
			"rotation": [90, 0, 0],
			"translation": [-1, 0, 8.25]
		},
		"gui": {
			"rotation": [90, 0, 0]
		},
		"head": {
			"rotation": [90, 25, 0],
			"translation": [0, 11.25, 13.5]
		},
		"fixed": {
			"rotation": [90, 0, 0],
			"translation": [0, 0, 7]
		}
	},
	"groups": [
		{
			"name": "dx0812",
			"origin": [8, 8, 8],
			"color": 0,
			"children": [0, 1, 2, 3, 4, 5, 6, 7, 8, 9, 10, 11, 12, 13, 14, 15, 16, 17, 18, 19, 20, 21, 22, 23, 24, 25, 26, 27, 28, 29, 30, 31, 32]
		}
	]
}